{
    "1426683292140175380": {
        "nivel": 11,
        "xp": 602,
        "tickets": 2,
        "lastTicketUpdate": 1778421735621,
        "pokedex": [
            "Arrow",
            "CatArrow",
            "Aro-Aplastado",
            "Aro-Light",
            "Brightrrow",
            "ArrowDerretido",
            "Arrow Distorsionado",
            "FireRrow",
            "ArrowHD",
            "Aro-Bot",
            "PixelArrow",
            "BigArrow",
            "ArrowDistorsion",
            "ArrowBlur"
        ],
        "warningActivo": true,
        "warning": false,
        "pity": 0
    },
    "1324554191531671573": {
        "nivel": 6,
        "xp": 55,
        "tickets": 3,
        "lastTicketUpdate": 1778104157969,
        "pokedex": [
            "InverseArrow",
            "CatArrow",
            "Aro-Light",
            "ArrowDistorsion",
            "Arrow",
            "AlienArrow"
        ],
        "warningActivo": false,
        "warning": true,
        "pity": 1
    },
    "1499599530235134044": {
        "nivel": 10,
        "xp": 197,
        "tickets": 2,
        "lastTicketUpdate": 1778421751448,
        "pokedex": [
            "Arrow",
            "CatArrow",
            "Aro-Bot",
            "Aro-Aplastado",
            "InverseArrow",
            "Aro-Light",
            "ArrowHD",
            "RareArrow"
        ],
        "warning": false,
        "pity": 3
    },
    "1456529970129272852": {
        "nivel": 3,
        "xp": 75,
        "tickets": 0,
        "lastTicketUpdate": 1777853137143,
        "pokedex": [
            "Arrow",
            "Aro-Light",
            "InverseArrow"
        ],
        "warning": false,
        "pity": 2
    },
    "1074028443462795304": {
        "nivel": 1,
        "xp": 0,
        "tickets": 3,
        "lastTicketUpdate": 1778026611972,
        "pokedex": [],
        "warning": false,
        "pity": 0
    },
    "1389346569974976512": {
        "nivel": 1,
        "xp": 0,
        "tickets": 3,
        "lastTicketUpdate": 1778029006609,
        "pokedex": [],
        "warning": false,
        "pity": 0
    },
    "748708882142068957": {
        "nivel": 2,
        "xp": 75,
        "tickets": 3,
        "lastTicketUpdate": 1778034124943,
        "pokedex": [
            "Arrow-Sus",
            "Aro-Light",
            "ArrowIRL"
        ],
        "warning": true,
        "pity": 3
    },
    "1091809750729117848": {
        "nivel": 1,
        "xp": 0,
        "tickets": 3,
        "lastTicketUpdate": 1778033054707,
        "pokedex": [],
        "warning": false,
        "pity": 0
    }
}